<?xml version="1.0" encoding="utf-8" ?>
<dwsync>
<file name="dim-des-2.html" server="victoriousnerd.pairserver.com//usr/home/victoriousnerd/public_html/" local="133571667300000000" remote="133571691130000000" Dst="2" />
<file name="dim-des-6.html" server="victoriousnerd.pairserver.com//usr/home/victoriousnerd/public_html/" local="133571667310000000" remote="133571691130000000" Dst="2" />
<file name="dim-des-3.html" server="victoriousnerd.pairserver.com//usr/home/victoriousnerd/public_html/" local="133571667300000000" remote="133571691130000000" Dst="2" />
<file name="dim-des-7.html" server="victoriousnerd.pairserver.com//usr/home/victoriousnerd/public_html/" local="133571667310000000" remote="133571691130000000" Dst="2" />
<file name="dim-des-1.html" server="victoriousnerd.pairserver.com//usr/home/victoriousnerd/public_html/" local="133571667300000000" remote="133571691130000000" Dst="2" />
<file name="dim-des-5.html" server="victoriousnerd.pairserver.com//usr/home/victoriousnerd/public_html/" local="133571667310000000" remote="133571691130000000" Dst="2" />
<file name="dim-des-9.html" server="victoriousnerd.pairserver.com//usr/home/victoriousnerd/public_html/" local="133571667310000000" remote="133571691140000000" Dst="2" />
<file name="dim-des-8.html" server="victoriousnerd.pairserver.com//usr/home/victoriousnerd/public_html/" local="133571667310000000" remote="133571691140000000" Dst="2" />
<file name="dim-des-4.html" server="victoriousnerd.pairserver.com//usr/home/victoriousnerd/public_html/" local="133571667300000000" remote="133571691130000000" Dst="2" />
</dwsync>